SE21003UNO/__init__.py
SE21003UNO/metodos.py
se21003uno-1.0.0.dist-info/licenses/LICENSE
se21003uno-1.0.0.dist-info/METADATA
se21003uno-1.0.0.dist-info/WHEEL
se21003uno-1.0.0.dist-info/top_level.txt
se21003uno-1.0.0.dist-info/RECORD
